Metadata-Version: 2.1
Name: org-mode-agenda
Version: 0.4
Summary: Import icalendar agendas to Orgmode
Home-page: https://gitlab.com/Titan-C/org-mode-agenda
Author: Óscar Nájera
Author-email: hi@oscarnajera.com
License: GNU General Public License v3 or later (GPLv3+)
Platform: UNKNOWN
Classifier: Programming Language :: Python :: 3
Classifier: License :: OSI Approved :: GNU General Public License v3 or later (GPLv3+)
Requires-Python: >=3.6
